sphinx_llm/__init__.py
sphinx_llm/_version.py
sphinx_llm/docref.py
sphinx_llm/txt.py
sphinx_llm/version.py
sphinx_llm/tests/__init__.py
sphinx_llm/tests/test_txt.py
sphinx_llm-0.1.3.dist-info/METADATA
sphinx_llm-0.1.3.dist-info/WHEEL
sphinx_llm-0.1.3.dist-info/licenses/LICENSE
sphinx_llm-0.1.3.dist-info/RECORD
