Metadata-Version: 2.4
Name: sphinx-llm
Version: 0.1.3
Project-URL: Documentation, https://github.com/jacobtomlinson/sphinx-llm#readme
Project-URL: Issues, https://github.com/jacobtomlinson/sphinx-llm/issues
Project-URL: Source, https://github.com/jacobtomlinson/sphinx-llm
Author-email: Jacob Tomlinson <jacob@tomlinson.email>
License: BSD 3-Clause License
License-File: LICENSE
Classifier: Development Status :: 4 - Beta
Classifier: Programming Language :: Python
Classifier: Programming Language :: Python :: 3.8
Classifier: Programming Language :: Python :: 3.9
Classifier: Programming Language :: Python :: 3.10
Classifier: Programming Language :: Python :: 3.11
Classifier: Programming Language :: Python :: 3.12
Classifier: Programming Language :: Python :: Implementation :: CPython
Classifier: Programming Language :: Python :: Implementation :: PyPy
Requires-Python: >=3.9
Requires-Dist: sphinx-markdown-builder>=0.6.8
Requires-Dist: sphinx>=5
Provides-Extra: gen
Requires-Dist: langchain-ollama>=0.2.0; extra == 'gen'
